jupyterlab_lavender/__init__.py
jupyterlab_lavender/_version.py
jupyterlab_lavender-0.1.1.data/data/share/jupyter/labextensions/jupyterlab_lavender/package.json
jupyterlab_lavender-0.1.1.data/data/share/jupyter/labextensions/jupyterlab_lavender/static/496.798adc717192cd1d151e.js
jupyterlab_lavender-0.1.1.data/data/share/jupyter/labextensions/jupyterlab_lavender/static/remoteEntry.0d12dbd7ac62dc5b426b.js
jupyterlab_lavender-0.1.1.data/data/share/jupyter/labextensions/jupyterlab_lavender/static/style.js
jupyterlab_lavender-0.1.1.data/data/share/jupyter/labextensions/jupyterlab_lavender/static/third-party-licenses.json
jupyterlab_lavender-0.1.1.data/data/share/jupyter/labextensions/jupyterlab_lavender/themes/jupyterlab_lavender/index.css
jupyterlab_lavender-0.1.1.data/data/share/jupyter/labextensions/jupyterlab_lavender/themes/jupyterlab_lavender/index.js
jupyterlab_lavender-0.1.1.data/data/share/jupyter/labextensions/jupyterlab_lavender/install.json
jupyterlab_lavender-0.1.1.dist-info/METADATA
jupyterlab_lavender-0.1.1.dist-info/WHEEL
jupyterlab_lavender-0.1.1.dist-info/licenses/LICENSE
jupyterlab_lavender-0.1.1.dist-info/RECORD
