Metadata-Version: 2.1
Name: jupyterlab_lavender
Version: 0.1.1
Summary: JupyterLab theme extension with dark background and low saturation
Project-URL: Homepage, https://github.com/tinjano/jupyterlab_lavender
Project-URL: Bug Tracker, https://github.com/tinjano/jupyterlab_lavender/issues
Project-URL: Repository, https://github.com/tinjano/jupyterlab_lavender.git
Author-email: tinjano <tinjano@proton.me>
License: MIT License
License-File: LICENSE
Classifier: Framework :: Jupyter
Classifier: Framework :: Jupyter :: JupyterLab
Classifier: Framework :: Jupyter :: JupyterLab :: 4
Classifier: Framework :: Jupyter :: JupyterLab :: Extensions
Classifier: Framework :: Jupyter :: JupyterLab :: Extensions :: Prebuilt
Classifier: License :: OSI Approved :: BSD License
Classifier: Programming Language :: Python
Classifier: Programming Language :: Python :: 3
Classifier: Programming Language :: Python :: 3.8
Classifier: Programming Language :: Python :: 3.9
Classifier: Programming Language :: Python :: 3.10
Classifier: Programming Language :: Python :: 3.11
Classifier: Programming Language :: Python :: 3.12
Requires-Python: >=3.8
